README.md
setup.cfg
setup.py
dummy_py/__init__.py
dummy_py.egg-info/PKG-INFO
dummy_py.egg-info/SOURCES.txt
dummy_py.egg-info/dependency_links.txt
dummy_py.egg-info/not-zip-safe
dummy_py.egg-info/requires.txt
dummy_py.egg-info/top_level.txt
dummy_py/audio/__init__.py
dummy_py/audio/mfcc.py
dummy_py/common/__init__.py
dummy_py/common/io.py
dummy_py/common/lazy.py
dummy_py/common/log.py
dummy_py/common/orm.py
dummy_py/common/sequence.py
dummy_py/common/take_fn.py
dummy_py/tf_parts/__init__.py
dummy_py/tf_parts/_type_hint.py
dummy_py/tf_parts/g_attn.py
dummy_py/tf_parts/rnn.py
dummy_py/tf_utils/__init__.py
dummy_py/tf_utils/helper.py
dummy_py/tf_utils/name_scope.py
dummy_py/tf_utils/utils.py