Metadata-Version: 1.0
Name: dummy-py
Version: 1.7
Summary: afpro's python library for dummies
Home-page: https://github.com/afpro/dummy_py
Author: afpro
Author-email: admin@afpro.net
License: Apache
Platform: UNKNOWN
